LICENSE
README.md
pyproject.toml
setup.py
src/launch_generator/__init__.py
src/launch_generator/base_generator.py
src/launch_generator/common_generator.py
src/launch_generator/container_generator.py
src/launch_generator/event_handler_generator.py
src/launch_generator/generator.py
src/launch_generator/group_generator.py
src/launch_generator/timer_generator.py
src/launch_generator/utils.py
src/launch_generator.egg-info/PKG-INFO
src/launch_generator.egg-info/SOURCES.txt
src/launch_generator.egg-info/dependency_links.txt
src/launch_generator.egg-info/requires.txt
src/launch_generator.egg-info/top_level.txt
test/test_generator.py