Metadata-Version: 2.1
Name: launch-generator
Version: 0.5.0
Summary: The package `launch-generator` is a tool to easily generate launch descriptions for ROS 2.
Home-page: https://github.com/Tacha-S/launch_generator
Author: Tatsuro Sakaguchi
Author-email: tatsuro.sakaguchi@g.softbank.co.jp
License: UNKNOWN
Platform: UNKNOWN
License-File: LICENSE
